colorframe/__init__.py
colorframe/__main__.py
colorframe/api.py
colorframe/border.py
colorframe/utils.py
colorframe-0.3.0.dist-info/METADATA
colorframe-0.3.0.dist-info/WHEEL
colorframe-0.3.0.dist-info/licenses/LICENSE
colorframe-0.3.0.dist-info/RECORD
