Metadata-Version: 2.3
Name: colorframe
Version: 0.3.0
Summary: Python utility to add borders to my photography pictures
Project-URL: homepage, https://github.com/fsoubelet/ColorFrame
Project-URL: repository, https://github.com/fsoubelet/ColorFrame
Author-email: Felix Soubelet <felix.soubelet@cern.ch>
License-Expression: MIT
License-File: LICENSE
Classifier: Development Status :: 5 - Production/Stable
Classifier: License :: OSI Approved :: MIT License
Classifier: Natural Language :: English
Classifier: Operating System :: OS Independent
Classifier: Programming Language :: Python :: 3 :: Only
Classifier: Programming Language :: Python :: 3.9
Classifier: Programming Language :: Python :: 3.10
Classifier: Programming Language :: Python :: 3.11
Classifier: Programming Language :: Python :: 3.12
Classifier: Programming Language :: Python :: Implementation :: CPython
Classifier: Topic :: Scientific/Engineering
Classifier: Topic :: Software Development :: Libraries :: Python Modules
Classifier: Typing :: Typed
Requires-Python: >=3.9
Requires-Dist: joblib>=1.3
Requires-Dist: loguru<1.0
Requires-Dist: pillow>=10.0
Requires-Dist: typer>=0.10
